pyfsdb_viewer/__init__.py
pyfsdb_viewer/dataloader.py
pyfsdb_viewer/pyfsdb_viewer.css
pyfsdb_viewer/view.py
pyfsdb_viewer/dataloader/__init__.py
pyfsdb_viewer/dataloader/fsdbloader.py
pyfsdb_viewer/dataloader/processloader.py
pyfsdb_viewer-0.7.2.dist-info/METADATA
pyfsdb_viewer-0.7.2.dist-info/WHEEL
pyfsdb_viewer-0.7.2.dist-info/entry_points.txt
pyfsdb_viewer-0.7.2.dist-info/top_level.txt
pyfsdb_viewer-0.7.2.dist-info/RECORD
