Metadata-Version: 2.1
Name: pyfsdb-viewer
Version: 0.7.2
Summary: A pyfsdb and textual based viewer
Home-page: https://github.com/gawseed/pyfsdb-viewer
Author: Wes Hardaker
Author-email: opensource@hardakers.net
Classifier: Programming Language :: Python :: 3
Classifier: Operating System :: OS Independent
Requires-Python: >=3.6
Requires-Dist: pyfsdb (>=2.3.4)
Requires-Dist: textual (>=0.32.0)
